Metadata-Version: 2.1
Name: t5-podcast-summariser
Version: 0.0.1
Summary: Podcast Transcript Summarisation
Home-page: UNKNOWN
Author: Paul Owoicho
Author-email: paulowoicho@gmail.com
License: UNKNOWN
Platform: UNKNOWN
